{"response":{"game_count":48,"games":[{"appid":550,"name":"Left 4 Dead 2","playtime_forever":2019,"img_icon_url":"7d5a243f9500d2f8467312822f8af2a2928777ed","img_logo_url":"205863cc21e751a576d6fff851984b3170684142","has_community_visible_stats":true,"playtime_windows_forever":144,"playtime_mac_forever":0,"playtime_linux_forever":0},{"appid":105600,"name":"Terraria","playtime_forever":707,"img_icon_url":"858961e95fbf869f136e1770d586e0caefd4cfac","img_logo_url":"783399da7d865b7b5b1560891b1e9463345e8fa9","has_community_visible_stats":true,"playtime_windows_forever":707,"playtime_mac_forever":0,"playtime_linux_forever":0},{"appid":239030,"name":"Papers, Please","playtime_forever":879,"img_icon_url":"102e22fc7e0689cb5a9d8cfdd5a6725d571d1a0f","img_logo_url":"eb4c045f73f9a4b1bac708e70fb12f12cd53010f","has_community_visible_stats":true,"playtime_windows_forever":116,"playtime_mac_forever":0,"playtime_linux_forever":0},{"appid":274920,"name":"FaceRig","playtime_forever":286,"img_icon_url":"c25aa8ad9cb85e7e132c61f8d32fd102954e3954","img_logo_url":"2cbcee5767c0cc33fdd94d9260094b576c6b842e","has_community_visible_stats":true,"playtime_windows_forever":1,"playtime_mac_forever":0,"playtime_linux_forever":0},{"appid":251570,"name":"7 Days to Die","playtime_forever":20558,"img_icon_url":"f6515dd177b2992aebcb563151fbe836a600f364","img_logo_url":"31488b068ae8975a942c8c5170b3266c1bf9a526","has_community_visible_stats":true,"playtime_windows_forever":8719,"playtime_mac_forever":0,"playtime_linux_forever":0},{"appid":292120,"name":"FINAL FANTASY XIII","playtime_forever":1880,"img_icon_url":"83c929d4965963f6e0bc17969a2599e7829ac23d","img_logo_url":"e9650bfd8e5af872bb7972ec2da9b9bd95ef123b","has_community_visible_stats":true,"playtime_windows_forever":0,"playtime_mac_forever":0,"playtime_linux_forever":0},{"appid":243470,"name":"Watch_Dogs","playtime_forever":6525,"img_icon_url":"53368e59a196dfa9af66ecd32135939da97fa72e","img_logo_url":"8957636e0668d8913539aa535a8a508e3e54b1f4","playtime_windows_forever":0,"playtime_mac_forever":0,"playtime_linux_forever":0},{"appid":304430,"name":"INSIDE","playtime_forever":745,"img_icon_url":"047e00c80d6aca008ce5eaaf54df4d98c822ee19","img_logo_url":"330a1902986716b0ab8947c8571687403bb99d6e","has_community_visible_stats":true,"playtime_windows_forever":0,"playtime_mac_forever":0,"playtime_linux_forever":0},{"appid":327890,"name":"I am Bread","playtime_forever":62,"img_icon_url":"40b2f1ff3dd97df35c094f4d8e8f2e98b8f75eee","img_logo_url":"8f0109409b5b196e4d8be175529d23a3d5fbb140","has_community_visible_stats":true,"playtime_windows_forever":0,"playtime_mac_forever":0,"playtime_linux_forever":0},{"appid":305620,"name":"The Long Dark","playtime_forever":1812,"img_icon_url":"e26b78087b75d5e002e92f2bdd73ce6fc4861e56","img_logo_url":"0c8eff00cce79bf9a2b19a6be1b495fc6229573e","has_community_visible_stats":true,"playtime_windows_forever":0,"playtime_mac_forever":0,"playtime_linux_forever":0},{"appid":333600,"name":"NEKOPARA Vol. 1","playtime_forever":314,"img_icon_url":"dc8a35b04deece2b870c4ea8c5e46283d822932e","img_logo_url":"5a01f7640ed0554e57b7eec2ec8d632fd874cd75","has_community_visible_stats":true,"playtime_windows_forever":0,"playtime_mac_forever":0,"playtime_linux_forever":0},{"appid":346110,"name":"ARK: Survival Evolved","playtime_forever":121,"img_icon_url":"fef1799533131c10f538d2dd697bbbd89e663265","img_logo_url":"58a660ddb7ed1864656ec65e4c18d6edd3bbf512","has_community_visible_stats":true,"playtime_windows_forever":0,"playtime_mac_forever":0,"playtime_linux_forever":0},{"appid":407530,"name":"ARK: Survival Of The Fittest","playtime_forever":0,"img_icon_url":"807c673cddebbfee0700a947a75f4872ad136e9b","img_logo_url":"870478f8ba64ce675aa232829c046fbce3bdbdde","playtime_windows_forever":0,"playtime_mac_forever":0,"playtime_linux_forever":0},{"appid":287290,"name":"Resident Evil Revelations 2","playtime_forever":1875,"img_icon_url":"0ec692bbc91bbff0b455faef6cb2b8a37bbbca93","img_logo_url":"dbd99a34dde062952221c88b3a649ea9c18038a2","has_community_visible_stats":true,"playtime_windows_forever":0,"playtime_mac_forever":0,"playtime_linux_forever":0},{"appid":221040,"name":"Resident Evil 6","playtime_forever":846,"img_icon_url":"0a0832a59b6c0a4ffa995b0343892729fe61ec1b","img_logo_url":"2398457399f20b979f0e5d0641262560a72408d5","has_community_visible_stats":true,"playtime_windows_forever":0,"playtime_mac_forever":0,"playtime_linux_forever":0},{"appid":381210,"name":"Dead by Daylight","playtime_forever":2520,"img_icon_url":"3d52bda003b28428330a6a08f4b3e1f12a7d4955","img_logo_url":"78a3f76693dbcd5dd80b5fcf531e8b81b3dd3163","has_community_visible_stats":true,"playtime_windows_forever":150,"playtime_mac_forever":0,"playtime_linux_forever":0},{"appid":385800,"name":"NEKOPARA Vol. 0","playtime_forever":0,"img_icon_url":"dc8a35b04deece2b870c4ea8c5e46283d822932e","img_logo_url":"b761129a809fe1d1da223e47429daabb360c2384","has_community_visible_stats":true,"playtime_windows_forever":0,"playtime_mac_forever":0,"playtime_linux_forever":0},{"appid":391540,"name":"Undertale","playtime_forever":659,"img_icon_url":"2ce672b89b63ec1e70d2f12862e72eb4a33e9268","img_logo_url":"ae953fb87a0fd4958ca21995226c065f33290eba","playtime_windows_forever":0,"playtime_mac_forever":0,"playtime_linux_forever":0},{"appid":402020,"name":"The Park","playtime_forever":0,"img_icon_url":"2ef474452399e793d0bf35bf33bde321dd4e97e9","img_logo_url":"9ccd26cd6481f979c663011178e976c58d17ee46","has_community_visible_stats":true,"playtime_windows_forever":0,"playtime_mac_forever":0,"playtime_linux_forever":0},{"appid":420110,"name":"NEKOPARA Vol. 2","playtime_forever":27,"img_icon_url":"dc8a35b04deece2b870c4ea8c5e46283d822932e","img_logo_url":"263dedd8cd1785c619c4a680c7045ae8c4cc85b7","has_community_visible_stats":true,"playtime_windows_forever":1,"playtime_mac_forever":0,"playtime_linux_forever":0},{"appid":424840,"name":"Little Nightmares","playtime_forever":1121,"img_icon_url":"1904c041f963b5e2cb22b56c370444517cc4e288","img_logo_url":"2681ea83b77b831431b95ad69a8ad6036d1ab981","has_community_visible_stats":true,"playtime_windows_forever":359,"playtime_mac_forever":0,"playtime_linux_forever":0},{"appid":427520,"name":"Factorio","playtime_forever":1180,"img_icon_url":"267f5a89f36ab287e600a4e7d4e73d3d11f0fd7d","img_logo_url":"95e5aa627ae1481b1dea293f6db5954e8aa79f41","has_community_visible_stats":true,"playtime_windows_forever":175,"playtime_mac_forever":0,"playtime_linux_forever":0},{"appid":431960,"name":"Wallpaper Engine","playtime_forever":50,"img_icon_url":"e9dd5b58abec11692416bb2d036d3a4e523595c6","img_logo_url":"74bcecbde31f489e396f656910c2f70872dcb0f3","has_community_visible_stats":true,"playtime_windows_forever":0,"playtime_mac_forever":0,"playtime_linux_forever":0},{"appid":438100,"name":"VRChat","playtime_forever":36,"img_icon_url":"52c5f93bd9f8de008307f5fad95023600267462c","img_logo_url":"62385c4bb53297d192a76829fce5d05b1f28ab90","playtime_windows_forever":0,"playtime_mac_forever":0,"playtime_linux_forever":0},{"appid":365590,"name":"Tom Clancy's The Division","playtime_forever":525,"img_icon_url":"93be9eec9ea09ee3cbc0f04de58f1c87a24b18f5","img_logo_url":"1fcb383a3dc433690068a7d49373f81a4bbe5ade","playtime_windows_forever":0,"playtime_mac_forever":0,"playtime_linux_forever":0},{"appid":524440,"name":"Tom Clancy's The Division PTS","playtime_forever":0,"img_icon_url":"93be9eec9ea09ee3cbc0f04de58f1c87a24b18f5","img_logo_url":"e82e56c842f3628dfe29cffc7a3b38a6129bee0e","playtime_windows_forever":0,"playtime_mac_forever":0,"playtime_linux_forever":0},{"appid":481510,"name":"Night in the Woods","playtime_forever":44,"img_icon_url":"8daeec5fe750eab2eb88f5060fa8152373289d04","img_logo_url":"f7e677cef75c04b719747dc892fa1411ecd7065f","has_community_visible_stats":true,"playtime_windows_forever":44,"playtime_mac_forever":0,"playtime_linux_forever":0},{"appid":447040,"name":"Watch_Dogs 2","playtime_forever":2550,"img_icon_url":"49dc5c3e4053e40159ffa73d2121daadbc467fe2","img_logo_url":"7b99c7302fdf12b5eb3ccc2a0592368986a89686","playtime_windows_forever":0,"playtime_mac_forever":0,"playtime_linux_forever":0},{"appid":319630,"name":"Life is Strange™","playtime_forever":160,"img_icon_url":"e54b13da0710a35e7088664a77632e79157d8332","img_logo_url":"e92d2b3a0c01be3bdd77ec665a3014028efaa105","has_community_visible_stats":true,"playtime_windows_forever":0,"playtime_mac_forever":0,"playtime_linux_forever":0},{"appid":438740,"name":"Friday the 13th: The Game","playtime_forever":48,"img_icon_url":"42b5e4d9df60f86b00b7b48a7061657475740030","img_logo_url":"d023067634eb03001ecdbf511ca5b3f56e38419c","has_community_visible_stats":true,"playtime_windows_forever":0,"playtime_mac_forever":0,"playtime_linux_forever":0},{"appid":578080,"name":"PLAYERUNKNOWN'S BATTLEGROUNDS","playtime_forever":3929,"img_icon_url":"93d896e7d7a42ae35c1d77239430e1d90bc82cae","img_logo_url":"2d2732a33511b58c69aff6b098a22687a3bb8533","has_community_visible_stats":true,"playtime_windows_forever":0,"playtime_mac_forever":0,"playtime_linux_forever":0},{"appid":602520,"name":"NEKOPARA Vol. 3","playtime_forever":496,"img_icon_url":"dc8a35b04deece2b870c4ea8c5e46283d822932e","img_logo_url":"ec3e4cb68ed9955a35f7252181cd29c9d744185b","has_community_visible_stats":true,"playtime_windows_forever":0,"playtime_mac_forever":0,"playtime_linux_forever":0},{"appid":698780,"name":"Doki Doki Literature Club","playtime_forever":15,"img_icon_url":"2bf8ed528d8f251428435a6f6ffc8e4e8e4b294c","img_logo_url":"76c3e09407e445568c9bb32d77bf364168ea45ed","playtime_windows_forever":0,"playtime_mac_forever":0,"playtime_linux_forever":0},{"appid":739630,"name":"Phasmophobia","playtime_forever":1654,"img_icon_url":"125673b382059f666ec81477173380a76e1df0be","img_logo_url":"e63390ac4ae4bf78787e09f5345629eb5955c6f1","playtime_windows_forever":1654,"playtime_mac_forever":0,"playtime_linux_forever":0},{"appid":746650,"name":"NEKOPARA OVA Extra","playtime_forever":23,"img_icon_url":"28f70d987f41256ea92c592a4a9c32fb96d0eab3","img_logo_url":"027754986e24dd871cf1ef0e528e96634dda7a63","playtime_windows_forever":0,"playtime_mac_forever":0,"playtime_linux_forever":0},{"appid":909420,"name":"NEKOPARA OVA Extra: NEKOPARA Extra OVA Non-Credit Ending Movie","playtime_forever":0,"img_icon_url":"","img_logo_url":"","playtime_windows_forever":0,"playtime_mac_forever":0,"playtime_linux_forever":0},{"appid":755790,"name":"Ring of Elysium","playtime_forever":67,"img_icon_url":"bff111ed4307fc769143eb3d652fb940c363e37e","img_logo_url":"94a7542fba330caa8e34946a2e5d53f0bd6a89d9","playtime_windows_forever":0,"playtime_mac_forever":0,"playtime_linux_forever":0},{"appid":774171,"name":"Muse Dash","playtime_forever":1108,"img_icon_url":"e0f4a24aa5b44887dc3467ee3e9ceabf46082041","img_logo_url":"c27a2910578c7b6ca7ca638510dc88472b72a26d","has_community_visible_stats":true,"playtime_windows_forever":1108,"playtime_mac_forever":0,"playtime_linux_forever":0},{"appid":570940,"name":"DARK SOULS™: REMASTERED","playtime_forever":2140,"img_icon_url":"d74cfa4f3a2070f45ad8ce44e5f61a6507ee00b6","img_logo_url":"fbad2989ed9549c4d456eb91fb28e0e6da54af9c","has_community_visible_stats":true,"playtime_windows_forever":2140,"playtime_mac_forever":0,"playtime_linux_forever":0},{"appid":440900,"name":"Conan Exiles","playtime_forever":568,"img_icon_url":"399859f8bdaeef066f14029d5f1910960545fbd9","img_logo_url":"554f691dfcb02f6969179774dd7b181532e70432","has_community_visible_stats":true,"playtime_windows_forever":0,"playtime_mac_forever":0,"playtime_linux_forever":0},{"appid":931180,"name":"Conan Exiles - Testlive Client","playtime_forever":0,"img_icon_url":"67a32c9bdd0738df619162c70bdebfe8a735abec","img_logo_url":"d27cbd7391566bcd59dfd4e6af6e49db12180789","playtime_windows_forever":0,"playtime_mac_forever":0,"playtime_linux_forever":0},{"appid":888790,"name":"Sabbat of the Witch","playtime_forever":970,"img_icon_url":"c09ee2699d212926b2faafbbcaa35d7a55ff6ab6","img_logo_url":"52053f7fa529c78680944a8f0bdd5d4e686fad38","has_community_visible_stats":true,"playtime_windows_forever":3,"playtime_mac_forever":0,"playtime_linux_forever":0},{"appid":899970,"name":"NEKOPARA Extra","playtime_forever":104,"img_icon_url":"dc8a35b04deece2b870c4ea8c5e46283d822932e","img_logo_url":"c91f730b6b8abc0f46fce593d0b1d6c842e802cf","has_community_visible_stats":true,"playtime_windows_forever":0,"playtime_mac_forever":0,"playtime_linux_forever":0},{"appid":304390,"name":"For Honor","playtime_forever":59,"img_icon_url":"64dd8eca34f0b5faeda135f057da1973806852f2","img_logo_url":"7d851b600a101d37c1b2e3e542fe02a3013a3283","playtime_windows_forever":0,"playtime_mac_forever":0,"playtime_linux_forever":0},{"appid":654310,"name":"For Honor - Public Test","playtime_forever":0,"img_icon_url":"64dd8eca34f0b5faeda135f057da1973806852f2","img_logo_url":"fd4e6f834821573215fd71803958f2c0bb8411ec","playtime_windows_forever":0,"playtime_mac_forever":0,"playtime_linux_forever":0},{"appid":1172470,"name":"Apex Legends","playtime_forever":0,"img_icon_url":"070902d2389878ac4bf29efb5b92832c60bdf24e","img_logo_url":"6a3169969cd4a66c7ae29a4934990160bccea1e4","has_community_visible_stats":true,"playtime_windows_forever":0,"playtime_mac_forever":0,"playtime_linux_forever":0},{"appid":555000,"name":"GOAT OF DUTY","playtime_forever":0,"img_icon_url":"db089f15dc9d6efaa71611985c9826641acc2170","img_logo_url":"6f03b7fdf4de5f2d528a34a12db2ac96e447f55c","has_community_visible_stats":true,"playtime_windows_forever":0,"playtime_mac_forever":0,"playtime_linux_forever":0},{"appid":860510,"name":"Little Nightmares II","playtime_forever":427,"img_icon_url":"8875efb23a0fc1f079f227508d981f2cba82d735","img_logo_url":"19b6e7fc830b2a752891a9a23afdc3fe94dc5d6b","has_community_visible_stats":true,"playtime_windows_forever":427,"playtime_mac_forever":0,"playtime_linux_forever":0}]}}